streamlit_appbar/__init__.py
streamlit_appbar/frontend/build/asset-manifest.json
streamlit_appbar/frontend/build/bootstrap.min.css
streamlit_appbar/frontend/build/index.html
streamlit_appbar/frontend/build/precache-manifest.b93cf1b0f73f988e9967758a695097d4.js
streamlit_appbar/frontend/build/service-worker.js
streamlit_appbar/frontend/build/static/js/2.90178962.chunk.js
streamlit_appbar/frontend/build/static/js/2.90178962.chunk.js.LICENSE.txt
streamlit_appbar/frontend/build/static/js/2.90178962.chunk.js.map
streamlit_appbar/frontend/build/static/js/main.f5fad66e.chunk.js
streamlit_appbar/frontend/build/static/js/main.f5fad66e.chunk.js.map
streamlit_appbar/frontend/build/static/js/runtime-main.44d30fc2.js
streamlit_appbar/frontend/build/static/js/runtime-main.44d30fc2.js.map
streamlit_appbar-0.0.2.dist-info/LICENSE
streamlit_appbar-0.0.2.dist-info/METADATA
streamlit_appbar-0.0.2.dist-info/WHEEL
streamlit_appbar-0.0.2.dist-info/top_level.txt
streamlit_appbar-0.0.2.dist-info/RECORD
