Metadata-Version: 2.1
Name: streamlit-appbar
Version: 0.0.2
Summary: Streamlit appbar with button options
Home-page: https://github.com/victorC97/streamlit_appbar
Author: victorC97
Author-email: victor.cour@telecomnancy.net
License: UNKNOWN
Platform: UNKNOWN
Requires-Python: >=3.6
Requires-Dist: streamlit (>=0.63)
